AUTHOR.txt
CHANGES.txt
LICENSE.txt
README.txt
bootstrap.py
setup.py
src/z3c/__init__.py
src/z3c.contents.egg-info/PKG-INFO
src/z3c.contents.egg-info/SOURCES.txt
src/z3c.contents.egg-info/dependency_links.txt
src/z3c.contents.egg-info/namespace_packages.txt
src/z3c.contents.egg-info/not-zip-safe
src/z3c.contents.egg-info/requires.txt
src/z3c.contents.egg-info/top_level.txt
src/z3c/contents/BROWSER.txt
src/z3c/contents/README.txt
src/z3c/contents/__init__.py
src/z3c/contents/browser.py
src/z3c/contents/browser.zcml
src/z3c/contents/column.py
src/z3c/contents/configure.zcml
src/z3c/contents/contents.pt
src/z3c/contents/ftesting.zcml
src/z3c/contents/header.py
src/z3c/contents/interfaces.py
src/z3c/contents/search.pt
src/z3c/contents/testing.pt
src/z3c/contents/testing.py
src/z3c/contents/tests.py
src/z3c/contents/value.py